Metadata-Version: 2.4
Name: image-processing-tania-test
Version: 0.0.1
Summary: Image Processing Package using Skimag
Home-page: https://github.com/taniacremonini/image-processing-package.git
Author: Tania Cremonini
Author-email: taninha_cremonini@hotmail.com
Requires-Python: >=3.5
Requires-Dist: matplotlib
Requires-Dist: numpy
Requires-Dist: scikit-image>=0.16.1
Dynamic: author
Dynamic: author-email
Dynamic: description
Dynamic: description-content-type
Dynamic: home-page
Dynamic: requires-dist
Dynamic: requires-python
Dynamic: summary
